JKflipflop/JKflipflop.vhdl
LIBRARY ieee;
USE ieee.std_logic_1164.ALL;

ENTITY my_jk IS
    PORT (
        j, k, clk, rst : IN STD_LOGIC;
        q, q_comp : OUT STD_LOGIC
    );
END my_jk;

ARCHITECTURE jk_arch OF my_jk IS
BEGIN
    PROCESS (j, k, clk, rst) IS
        VARIABLE output : STD_LOGIC := '0';
    BEGIN
        IF (rst = '1') THEN
            output := '0';
        ELSIF (rising_edge(clk)) THEN
            IF (j /= k) THEN
                output := j;
            ELSIF (j = '1' AND k = '1') THEN
                output := NOT output;
            END IF;
        END IF;
        q <= output;
        q_comp <= NOT output;
    END PROCESS;
END jk_arch;

JKflipflop/JKflipflopTB.vhdl
-- library ieee;
-- use ieee.std_logic_1164.all;
-- use ieee.std_logic_arith.all;
-- use ieee.std_logic_unsigned.all;

-- entity jk_tb is
-- end jk_tb;

-- architecture jk_arch of jk_tb is
--     signal j, k, clk, rst: std_logic := '0';
--     signal q, q_comp: std_logic;

--     component jk is
--         port(
--             j, k, clk, rst: in std_logic;
--             q, q_comp: out std_logic
--         );
--     end component jk;

-- begin
--     uut: jk
--     port map(j => j, k => k, clk => clk, rst => rst, q => q, q_comp => q_comp);

--     clk_process: process
--     begin
--         clk <= '0';
--         wait for 240 ns;

--         clk <= '1';
--         wait for 240 ns;
--     end process clk_process;

--     stimulus_process: process
--     begin
--         rst <= '1';
--         wait for 10 ns;

--         rst <= '0';
--         wait for 10 ns;

--         -- test case 1
--         j <= '0';
--         k <= '0';
--         wait for 240 ns;

--         -- test case 2
--         j <= '0';
--         k <= '1';
--         wait for 240 ns;

--         -- test case 3
--         j <= '1';
--         k <= '0';
--         wait for 240 ns;

--         -- test case 4
--         j <= '1';
--         k <= '1';
--         wait for 240 ns;

--         wait;
--     end process stimulus_process;
-- end jk_arch;


library ieee;
use ieee.std_logic_1164.all;

entity my_jk_tb is
end my_jk_tb;

architecture tb_arch of my_jk_tb is
    component my_jk is
        port (
            j, k, clk, rst: in std_logic;
            q, q_comp: out std_logic
        );
    end component my_jk;

    signal j_tb, k_tb, clk_tb, rst_tb, q_tb, q_comp_tb : std_logic := '0';
begin
    dut: my_jk port map (j => j_tb, k => k_tb, clk => clk_tb, rst => rst_tb, q => q_tb, q_comp => q_comp_tb);

    stimulus_proc: process
    begin
        rst_tb <= '1';
        clk_tb <= '0';
        j_tb <= '0';
        k_tb <= '0';
        wait for 10 ns;
        
        rst_tb <= '0';
        wait for 10 ns;
        
        clk_tb <= not clk_tb;
        wait for 10 ns;
        
        j_tb <= '1';  -- Example test case, change as needed
        k_tb <= '0';
        wait for 10 ns;
        
        j_tb <= '0';
        k_tb <= '1';
        wait for 10 ns;
        
        j_tb <= '1';
        k_tb <= '1';
        wait for 10 ns;
        
        -- Add more test cases or stimulus here
        
        wait;
    end process;
end tb_arch;

JKflipflop/result.vcd
$date
  Sun Feb 18 16:47:20 2024
$end
$version
  GHDL v0
$end
$timescale
  1 fs
$end
$scope module standard $end
$upscope $end
$scope module std_logic_1164 $end
$upscope $end
$scope module my_jk_tb $end
$var reg 1 ! j_tb $end
$var reg 1 " k_tb $end
$var reg 1 # clk_tb $end
$var reg 1 $ rst_tb $end
$var reg 1 % q_tb $end
$var reg 1 & q_comp_tb $end
$scope module dut $end
$var reg 1 ' j $end
$var reg 1 ( k $end
$var reg 1 ) clk $end
$var reg 1 * rst $end
$var reg 1 + q $end
$var reg 1 , q_comp $end
$upscope $end
$upscope $end
$enddefinitions $end
#0
0!
0"
1#
1$
0%
1&
0'
0(
1)
1*
0+
1,
#10000000
0#
0$
0)
0*
#20000000
1#
1)
#30000000
1"
0#
1(
0)
#40000000
1!
0"
1#
1%
0&
1'
0(
1)
1+
0,
#50000000
1"
0#
1(
0)
#60000000
1#
0%
1&
1)
0+
1,
#70000000
0#
0)
#80000000
1#
1%
0&
1)
1+
0,
#90000000
0#
0)
#100000000
1#
0%
1&
1)
0+
1,
#110000000
0#
0)
#120000000
1#
1%
0&
1)
1+
0,
#130000000
0#
0)
#140000000
1#
0%
1&
1)
0+
1,
#150000000
0#
0)
#160000000
1#
1%
0&
1)
1+
0,
#170000000
0#
0)
#180000000
1#
0%
1&
1)
0+
1,
#190000000
0#
0)
#200000000
1#
1%
0&
1)
1+
0,
#210000000
0#
0)
#220000000
1#
0%
1&
1)
0+
1,
#230000000
0#
0)
#240000000
1#
1%
0&
1)
1+
0,
#250000000
0#
0)
#260000000
1#
0%
1&
1)
0+
1,
#270000000
0#
0)
#280000000
1#
1%
0&
1)
1+
0,
#290000000
0#
0)
#300000000
1#
0%
1&
1)
0+
1,
#310000000
0#
0)
#320000000
1#
1%
0&
1)
1+
0,
#330000000
0#
0)
#340000000
1#
0%
1&
1)
0+
1,
#350000000
0#
0)
#360000000
1#
1%
0&
1)
1+
0,
#370000000
0#
0)
#380000000
1#
0%
1&
1)
0+
1,
#390000000
0#
0)
#400000000
1#
1%
0&
1)
1+
0,
#410000000
0#
0)
#420000000
1#
0%
1&
1)
0+
1,
#430000000
0#
0)
#440000000
1#
1%
0&
1)
1+
0,
#450000000
0#
0)
#460000000
1#
0%
1&
1)
0+
1,
#470000000
0#
0)
#480000000
1#
1%
0&
1)
1+
0,
#490000000
0#
0)
#500000000
1#
0%
1&
1)
0+
1,
#510000000
0#
0)
#520000000
1#
1%
0&
1)
1+
0,
#530000000
0#
0)
#540000000
1#
0%
1&
1)
0+
1,
#550000000
0#
0)
#560000000
1#
1%
0&
1)
1+
0,
#570000000
0#
0)
#580000000
1#
0%
1&
1)
0+
1,
#590000000
0#
0)
#600000000
1#
1%
0&
1)
1+
0,
#610000000
0#
0)
#620000000
1#
0%
1&
1)
0+
1,
#630000000
0#
0)
#640000000
1#
1%
0&
1)
1+
0,
#650000000
0#
0)
#660000000
1#
0%
1&
1)
0+
1,
#670000000
0#
0)
#680000000
1#
1%
0&
1)
1+
0,
#690000000
0#
0)
#700000000
1#
0%
1&
1)
0+
1,
#710000000
0#
0)
#720000000
1#
1%
0&
1)
1+
0,
#730000000
0#
0)
#740000000
1#
0%
1&
1)
0+
1,
#750000000
0#
0)
#760000000
1#
1%
0&
1)
1+
0,
#770000000
0#
0)
#780000000
1#
0%
1&
1)
0+
1,
#790000000
0#
0)
#800000000
1#
1%
0&
1)
1+
0,
#810000000
0#
0)
#820000000
1#
0%
1&
1)
0+
1,
#830000000
0#
0)
#840000000
1#
1%
0&
1)
1+
0,
#850000000
0#
0)
#860000000
1#
0%
1&
1)
0+
1,
#870000000
0#
0)
#880000000
1#
1%
0&
1)
1+
0,
#890000000
0#
0)
#900000000
1#
0%
1&
1)
0+
1,
#910000000
0#
0)
#920000000
1#
1%
0&
1)
1+
0,
#930000000
0#
0)
#940000000
1#
0%
1&
1)
0+
1,
#950000000
0#
0)
#960000000
1#
1%
0&
1)
1+
0,
#970000000
0#
0)
#980000000
1#
0%
1&
1)
0+
1,
#990000000
0#
0)
#1000000000
1#
1%
0&
1)
1+
0,
#1010000000
0#
0)
#1020000000
1#
0%
1&
1)
0+
1,
#1030000000
0#
0)
#1040000000
1#
1%
0&
1)
1+
0,
#1050000000
0#
0)
#1060000000
1#
0%
1&
1)
0+
1,
#1070000000
0#
0)
#1080000000
1#
1%
0&
1)
1+
0,
#1090000000
0#
0)
#1100000000
1#
0%
1&
1)
0+
1,
#1110000000
0#
0)
#1120000000
1#
1%
0&
1)
1+
0,
#1130000000
0#
0)
#1140000000
1#
0%
1&
1)
0+
1,
#1150000000
0#
0)
#1160000000
1#
1%
0&
1)
1+
0,
#1170000000
0#
0)
#1180000000
1#
0%
1&
1)
0+
1,
#1190000000
0#
0)
#1200000000
1#
1%
0&
1)
1+
0,
#1210000000
0#
0)
#1220000000
1#
0%
1&
1)
0+
1,
#1230000000
0#
0)
#1240000000
1#
1%
0&
1)
1+
0,
#1250000000
0#
0)
#1260000000
1#
0%
1&
1)
0+
1,
#1270000000
0#
0)
#1280000000
1#
1%
0&
1)
1+
0,
#1290000000
0#
0)
#1300000000
1#
0%
1&
1)
0+
1,
#1310000000
0#
0)
#1320000000
1#
1%
0&
1)
1+
0,
#1330000000
0#
0)
#1340000000
1#
0%
1&
1)
0+
1,
#1350000000
0#
0)
#1360000000
1#
1%
0&
1)
1+
0,
#1370000000
0#
0)
#1380000000
1#
0%
1&
1)
0+
1,
#1390000000
0#
0)
#1400000000
1#
1%
0&
1)
1+
0,
#1410000000
0#
0)
#1420000000
1#
0%
1&
1)
0+
1,
#1430000000
0#
0)
#1440000000
1#
1%
0&
1)
1+
0,
#1450000000
0#
0)
#1460000000
1#
0%
1&
1)
0+
1,
#1470000000
0#
0)
#1480000000
1#
1%
0&
1)
1+
0,
#1490000000
0#
0)
#1500000000
1#
0%
1&
1)
0+
1,
#1510000000
0#
0)
#1520000000
1#
1%
0&
1)
1+
0,
#1530000000
0#
0)
#1540000000
1#
0%
1&
1)
0+
1,
#1550000000
0#
0)
#1560000000
1#
1%
0&
1)
1+
0,
#1570000000
0#
0)
#1580000000
1#
0%
1&
1)
0+
1,
#1590000000
0#
0)
#1600000000
1#
1%
0&
1)
1+
0,
#1610000000
0#
0)
#1620000000
1#
0%
1&
1)
0+
1,
#1630000000
0#
0)
#1640000000
1#
1%
0&
1)
1+
0,
#1650000000
0#
0)
#1660000000
1#
0%
1&
1)
0+
1,
#1670000000
0#
0)
#1680000000
1#
1%
0&
1)
1+
0,
#1690000000
0#
0)
#1700000000
1#
0%
1&
1)
0+
1,
#1710000000
0#
0)
#1720000000
1#
1%
0&
1)
1+
0,
#1730000000
0#
0)
#1740000000
1#
0%
1&
1)
0+
1,
#1750000000
0#
0)
#1760000000
1#
1%
0&
1)
1+
0,
#1770000000
0#
0)
#1780000000
1#
0%
1&
1)
0+
1,
#1790000000
0#
0)
#1800000000
1#
1%
0&
1)
1+
0,
#1810000000
0#
0)
#1820000000
1#
0%
1&
1)
0+
1,
#1830000000
0#
0)
#1840000000
1#
1%
0&
1)
1+
0,
#1850000000
0#
0)
#1860000000
1#
0%
1&
1)
0+
1,
#1870000000
0#
0)
#1880000000
1#
1%
0&
1)
1+
0,
#1890000000
0#
0)
#1900000000
1#
0%
1&
1)
0+
1,
#1910000000
0#
0)
#1920000000
1#
1%
0&
1)
1+
0,
#1930000000
0#
0)
#1940000000
1#
0%
1&
1)
0+
1,
#1950000000
0#
0)
#1960000000
1#
1%
0&
1)
1+
0,
#1970000000
0#
0)
#1980000000
1#
0%
1&
1)
0+
1,
#1990000000
0#
0)
#2000000000
1#
1%
0&
1)
1+
0,
#2010000000
0#
0)
#2020000000
1#
0%
1&
1)
0+
1,
#2030000000
0#
0)
#2040000000
1#
1%
0&
1)
1+
0,
#2050000000
0#
0)
#2060000000
1#
0%
1&
1)
0+
1,
#2070000000
0#
0)
#2080000000
1#
1%
0&
1)
1+
0,
#2090000000
0#
0)
#2100000000
1#
0%
1&
1)
0+
1,
#2110000000
0#
0)
#2120000000
1#
1%
0&
1)
1+
0,
#2130000000
0#
0)
#2140000000
1#
0%
1&
1)
0+
1,
#2150000000
0#
0)
#2160000000
1#
1%
0&
1)
1+
0,
#2170000000
0#
0)
#2180000000
1#
0%
1&
1)
0+
1,
#2190000000
0#
0)
#2200000000
1#
1%
0&
1)
1+
0,
#2210000000
0#
0)
#2220000000
1#
0%
1&
1)
0+
1,
#2230000000
0#
0)
#2240000000
1#
1%
0&
1)
1+
0,
#2250000000
0#
0)
#2260000000
1#
0%
1&
1)
0+
1,
#2270000000
0#
0)
#2280000000
1#
1%
0&
1)
1+
0,
#2290000000
0#
0)
#2300000000
1#
0%
1&
1)
0+
1,
#2310000000
0#
0)
#2320000000
1#
1%
0&
1)
1+
0,
#2330000000
0#
0)
#2340000000
1#
0%
1&
1)
0+
1,
#2350000000
0#
0)
#2360000000
1#
1%
0&
1)
1+
0,
#2370000000
0#
0)
#2380000000
1#
0%
1&
1)
0+
1,
#2390000000
0#
0)
#2400000000
1#
1%
0&
1)
1+
0,
#2410000000
0#
0)
#2420000000
1#
0%
1&
1)
0+
1,
#2430000000
0#
0)
#2440000000
1#
1%
0&
1)
1+
0,
#2450000000
0#
0)
#2460000000
1#
0%
1&
1)
0+
1,
#2470000000
0#
0)
#2480000000
1#
1%
0&
1)
1+
0,
#2490000000
0#
0)
#2500000000
1#
0%
1&
1)
0+
1,
#2510000000
0#
0)
#2520000000
1#
1%
0&
1)
1+
0,
#2530000000
0#
0)
#2540000000
1#
0%
1&
1)
0+
1,
#2550000000
0#
0)
#2560000000
1#
1%
0&
1)
1+
0,
#2570000000
0#
0)
#2580000000
1#
0%
1&
1)
0+
1,
#2590000000
0#
0)
#2600000000
1#
1%
0&
1)
1+
0,
#2610000000
0#
0)
#2620000000
1#
0%
1&
1)
0+
1,
#2630000000
0#
0)
#2640000000
1#
1%
0&
1)
1+
0,
#2650000000
0#
0)
#2660000000
1#
0%
1&
1)
0+
1,
#2670000000
0#
0)
#2680000000
1#
1%
0&
1)
1+
0,
#2690000000
0#
0)
#2700000000
1#
0%
1&
1)
0+
1,
#2710000000
0#
0)
#2720000000
1#
1%
0&
1)
1+
0,
#2730000000
0#
0)
#2740000000
1#
0%
1&
1)
0+
1,
#2750000000
0#
0)
#2760000000
1#
1%
0&
1)
1+
0,
#2770000000
0#
0)
#2780000000
1#
0%
1&
1)
0+
1,
#2790000000
0#
0)
#2800000000
1#
1%
0&
1)
1+
0,
#2810000000
0#
0)
#2820000000
1#
0%
1&
1)
0+
1,
#2830000000
0#
0)
#2840000000
1#
1%
0&
1)
1+
0,
#2850000000
0#
0)
#2860000000
1#
0%
1&
1)
0+
1,
#2870000000
0#
0)
#2880000000
1#
1%
0&
1)
1+
0,
#2890000000
0#
0)
#2900000000
1#
0%
1&
1)
0+
1,
#2910000000
0#
0)
#2920000000
1#
1%
0&
1)
1+
0,
#2930000000
0#
0)
#2940000000
1#
0%
1&
1)
0+
1,
#2950000000
0#
0)
#2960000000
1#
1%
0&
1)
1+
0,
#2970000000
0#
0)
#2980000000
1#
0%
1&
1)
0+
1,
#2990000000
0#
0)
#3000000000
1#
1%
0&
1)
1+
0,
#3010000000
0#
0)
#3020000000
1#
0%
1&
1)
0+
1,
#3030000000
0#
0)
#3040000000
1#
1%
0&
1)
1+
0,
#3050000000
0#
0)
#3060000000
1#
0%
1&
1)
0+
1,
#3070000000
0#
0)
#3080000000
1#
1%
0&
1)
1+
0,
#3090000000
0#
0)
#3100000000
1#
0%
1&
1)
0+
1,
#3110000000
0#
0)
#3120000000
1#
1%
0&
1)
1+
0,
#3130000000
0#
0)
#3140000000
1#
0%
1&
1)
0+
1,
#3150000000
0#
0)
#3160000000
1#
1%
0&
1)
1+
0,
#3170000000
0#
0)
#3180000000
1#
0%
1&
1)
0+
1,
#3190000000
0#
0)
#3200000000
1#
1%
0&
1)
1+
0,
#3210000000
0#
0)
#3220000000
1#
0%
1&
1)
0+
1,
#3230000000
0#
0)
#3240000000
1#
1%
0&
1)
1+
0,
#3250000000
0#
0)
#3260000000
1#
0%
1&
1)
0+
1,
#3270000000
0#
0)
#3280000000
1#
1%
0&
1)
1+
0,
#3290000000
0#
0)
#3300000000
1#
0%
1&
1)
0+
1,
#3310000000
0#
0)
#3320000000
1#
1%
0&
1)
1+
0,
#3330000000
0#
0)
#3340000000
1#
0%
1&
1)
0+
1,
#3350000000
0#
0)
#3360000000
1#
1%
0&
1)
1+
0,
#3370000000
0#
0)
#3380000000
1#
0%
1&
1)
0+
1,
#3390000000
0#
0)
#3400000000
1#
1%
0&
1)
1+
0,
#3410000000
0#
0)
#3420000000
1#
0%
1&
1)
0+
1,
#3430000000
0#
0)
#3440000000
1#
1%
0&
1)
1+
0,
#3450000000
0#
0)
#3460000000
1#
0%
1&
1)
0+
1,
#3470000000
0#
0)
#3480000000
1#
1%
0&
1)
1+
0,
#3490000000
0#
0)
#3500000000
1#
0%
1&
1)
0+
1,
#3510000000
0#
0)
#3520000000
1#
1%
0&
1)
1+
0,
#3530000000
0#
0)
#3540000000
1#
0%
1&
1)
0+
1,
#3550000000
0#
0)
#3560000000
1#
1%
0&
1)
1+
0,
#3570000000
0#
0)
#3580000000
1#
0%
1&
1)
0+
1,
#3590000000
0#
0)
#3600000000
1#
1%
0&
1)
1+
0,
#3610000000
0#
0)
#3620000000
1#
0%
1&
1)
0+
1,
#3630000000
0#
0)
#3640000000
1#
1%
0&
1)
1+
0,
#3650000000
0#
0)
#3660000000
1#
0%
1&
1)
0+
1,
#3670000000
0#
0)
#3680000000
1#
1%
0&
1)
1+
0,
#3690000000
0#
0)
#3700000000
1#
0%
1&
1)
0+
1,
#3710000000
0#
0)
#3720000000
1#
1%
0&
1)
1+
0,
#3730000000
0#
0)
#3740000000
1#
0%
1&
1)
0+
1,
#3750000000
0#
0)
#3760000000
1#
1%
0&
1)
1+
0,
#3770000000
0#
0)
#3780000000
1#
0%
1&
1)
0+
1,
#3790000000
0#
0)
#3800000000
1#
1%
0&
1)
1+
0,
#3810000000
0#
0)
#3820000000
1#
0%
1&
1)
0+
1,
#3830000000
0#
0)
#3840000000
1#
1%
0&
1)
1+
0,
#3850000000
0#
0)
#3860000000
1#
0%
1&
1)
0+
1,
#3870000000
0#
0)
#3880000000
1#
1%
0&
1)
1+
0,
#3890000000
0#
0)
#3900000000
1#
0%
1&
1)
0+
1,
#3910000000
0#
0)
#3920000000
1#
1%
0&
1)
1+
0,
#3930000000
0#
0)
#3940000000
1#
0%
1&
1)
0+
1,
#3950000000
0#
0)
#3960000000
1#
1%
0&
1)
1+
0,
#3970000000
0#
0)
#3980000000
1#
0%
1&
1)
0+
1,
#3990000000
0#
0)
#4000000000
1#
1%
0&
1)
1+
0,
#4010000000
0#
0)
#4020000000
1#
0%
1&
1)
0+
1,
#4030000000
0#
0)
#4040000000
1#
1%
0&
1)
1+
0,
#4050000000
0#
0)
#4060000000
1#
0%
1&
1)
0+
1,
#4070000000
0#
0)
#4080000000
1#
1%
0&
1)
1+
0,
#4090000000
0#
0)
#4100000000
1#
0%
1&
1)
0+
1,
#4110000000
0#
0)
#4120000000
1#
1%
0&
1)
1+
0,
#4130000000
0#
0)
#4140000000
1#
0%
1&
1)
0+
1,
#4150000000
0#
0)
#4160000000
1#
1%
0&
1)
1+
0,
#4170000000
0#
0)
#4180000000
1#
0%
1&
1)
0+
1,
#4190000000
0#
0)
#4200000000
1#
1%
0&
1)
1+
0,
#4210000000
0#
0)
#4220000000
1#
0%
1&
1)
0+
1,
#4230000000
0#
0)
#4240000000
1#
1%
0&
1)
1+
0,
#4250000000
0#
0)
#4260000000
1#
0%
1&
1)
0+
1,
#4270000000
0#
0)
#4280000000
1#
1%
0&
1)
1+
0,
#4290000000
0#
0)
#4300000000
1#
0%
1&
1)
0+
1,
#4310000000
0#
0)
#4320000000
1#
1%
0&
1)
1+
0,
#4330000000
0#
0)
#4340000000
1#
0%
1&
1)
0+
1,
#4350000000
0#
0)
#4360000000
1#
1%
0&
1)
1+
0,
#4370000000
0#
0)
#4380000000
1#
0%
1&
1)
0+
1,
#4390000000
0#
0)
#4400000000
1#
1%
0&
1)
1+
0,
#4410000000
0#
0)
#4420000000
1#
0%
1&
1)
0+
1,
#4430000000
0#
0)
#4440000000
1#
1%
0&
1)
1+
0,
#4450000000
0#
0)
#4460000000
1#
0%
1&
1)
0+
1,
#4470000000
0#
0)
#4480000000
1#
1%
0&
1)
1+
0,
#4490000000
0#
0)
#4500000000
1#
0%
1&
1)
0+
1,
#4510000000
0#
0)
#4520000000
1#
1%
0&
1)
1+
0,
#4530000000
0#
0)
#4540000000
1#
0%
1&
1)
0+
1,
#4550000000
0#
0)
#4560000000
1#
1%
0&
1)
1+
0,
#4570000000
0#
0)
#4580000000
1#
0%
1&
1)
0+
1,
#4590000000
0#
0)
#4600000000
1#
1%
0&
1)
1+
0,
#4610000000
0#
0)
#4620000000
1#
0%
1&
1)
0+
1,
#4630000000
0#
0)
#4640000000
1#
1%
0&
1)
1+
0,
#4650000000
0#
0)
#4660000000
1#
0%
1&
1)
0+
1,
#4670000000
0#
0)
#4680000000
1#
1%
0&
1)
1+
0,
#4690000000
0#
0)
#4700000000
1#
0%
1&
1)
0+
1,
#4710000000
0#
0)
#4720000000
1#
1%
0&
1)
1+
0,
#4730000000
0#
0)
#4740000000
1#
0%
1&
1)
0+
1,
#4750000000
0#
0)
#4760000000
1#
1%
0&
1)
1+
0,
#4770000000
0#
0)
#4780000000
1#
0%
1&
1)
0+
1,
#4790000000
0#
0)
#4800000000
1#
1%
0&
1)
1+
0,
#4810000000
0#
0)
#4820000000
1#
0%
1&
1)
0+
1,
#4830000000
0#
0)
#4840000000
1#
1%
0&
1)
1+
0,
#4850000000
0#
0)
#4860000000
1#
0%
1&
1)
0+
1,
#4870000000
0#
0)
#4880000000
1#
1%
0&
1)
1+
0,
#4890000000
0#
0)
#4900000000
1#
0%
1&
1)
0+
1,
#4910000000
0#
0)
#4920000000
1#
1%
0&
1)
1+
0,
#4930000000
0#
0)
#4940000000
1#
0%
1&
1)
0+
1,
#4950000000
0#
0)
#4960000000
1#
1%
0&
1)
1+
0,
#4970000000
0#
0)
#4980000000
1#
0%
1&
1)
0+
1,
#4990000000
0#
0)
#5000000000
1#
1%
0&
1)
1+
0,
#5010000000
0#
0)
#5020000000
1#
0%
1&
1)
0+
1,
#5030000000
0#
0)
#5040000000
1#
1%
0&
1)
1+
0,
#5050000000
0#
0)
#5060000000
1#
0%
1&
1)
0+
1,
#5070000000
0#
0)
#5080000000
1#
1%
0&
1)
1+
0,
#5090000000
0#
0)
#5100000000
1#
0%
1&
1)
0+
1,
#5110000000
0#
0)
#5120000000
1#
1%
0&
1)
1+
0,
#5130000000
0#
0)
#5140000000
1#
0%
1&
1)
0+
1,
#5150000000
0#
0)
#5160000000
1#
1%
0&
1)
1+
0,
#5170000000
0#
0)
#5180000000
1#
0%
1&
1)
0+
1,
#5190000000
0#
0)
#5200000000
1#
1%
0&
1)
1+
0,
#5210000000
0#
0)
#5220000000
1#
0%
1&
1)
0+
1,
#5230000000
0#
0)
#5240000000
1#
1%
0&
1)
1+
0,
#5250000000
0#
0)
#5260000000
1#
0%
1&
1)
0+
1,
#5270000000
0#
0)
#5280000000
1#
1%
0&
1)
1+
0,
#5290000000
0#
0)
#5300000000
1#
0%
1&
1)
0+
1,
#5310000000
0#
0)
#5320000000
1#
1%
0&
1)
1+
0,
#5330000000
0#
0)
#5340000000
1#
0%
1&
1)
0+
1,
#5350000000
0#
0)
#5360000000
1#
1%
0&
1)
1+
0,
#5370000000
0#
0)
#5380000000
1#
0%
1&
1)
0+
1,
#5390000000
0#
0)
#5400000000
1#
1%
0&
1)
1+
0,
#5410000000
0#
0)
#5420000000
1#
0%
1&
1)
0+
1,
#5430000000
0#
0)
#5440000000
1#
1%
0&
1)
1+
0,
#5450000000
0#
0)
#5460000000
1#
0%
1&
1)
0+
1,
#5470000000
0#
0)
#5480000000
1#
1%
0&
1)
1+
0,
#5490000000
0#
0)
#5500000000
1#
0%
1&
1)
0+
1,
#5510000000
0#
0)
#5520000000
1#
1%
0&
1)
1+
0,
#5530000000
0#
0)
#5540000000
1#
0%
1&
1)
0+
1,
#5550000000
0#
0)
#5560000000
1#
1%
0&
1)
1+
0,
#5570000000
0#
0)
#5580000000
1#
0%
1&
1)
0+
1,
#5590000000
0#
0)
#5600000000
1#
1%
0&
1)
1+
0,
#5610000000
0#
0)
#5620000000
1#
0%
1&
1)
0+
1,
#5630000000
0#
0)
#5640000000
1#
1%
0&
1)
1+
0,
#5650000000
0#
0)
#5660000000
1#
0%
1&
1)
0+
1,
#5670000000
0#
0)
#5680000000
1#
1%
0&
1)
1+
0,
#5690000000
0#
0)
#5700000000
1#
0%
1&
1)
0+
1,
#5710000000
0#
0)
#5720000000
1#
1%
0&
1)
1+
0,
#5730000000
0#
0)
#5740000000
1#
0%
1&
1)
0+
1,
#5750000000
0#
0)
#5760000000
1#
1%
0&
1)
1+
0,
#5770000000
0#
0)
#5780000000
1#
0%
1&
1)
0+
1,
#5790000000
0#
0)
#5800000000
1#
1%
0&
1)
1+
0,
#5810000000
0#
0)
#5820000000
1#
0%
1&
1)
0+
1,
#5830000000
0#
0)
#5840000000
1#
1%
0&
1)
1+
0,
#5850000000
0#
0)
#5860000000
1#
0%
1&
1)
0+
1,
#5870000000
0#
0)
#5880000000
1#
1%
0&
1)
1+
0,
#5890000000
0#
0)
#5900000000
1#
0%
1&
1)
0+
1,
#5910000000
0#
0)
#5920000000
1#
1%
0&
1)
1+
0,
#5930000000
0#
0)
#5940000000
1#
0%
1&
1)
0+
1,
#5950000000
0#
0)
#5960000000
1#
1%
0&
1)
1+
0,
#5970000000
0#
0)
#5980000000
1#
0%
1&
1)
0+
1,
#5990000000
0#
0)
#6000000000
1#
1%
0&
1)
1+
0,
#6010000000
0#
0)
#6020000000
1#
0%
1&
1)
0+
1,
#6030000000
0#
0)
#6040000000
1#
1%
0&
1)
1+
0,
#6050000000
0#
0)
#6060000000
1#
0%
1&
1)
0+
1,
#6070000000
0#
0)
#6080000000
1#
1%
0&
1)
1+
0,
#6090000000
0#
0)
#6100000000
1#
0%
1&
1)
0+
1,
#6110000000
0#
0)
#6120000000
1#
1%
0&
1)
1+
0,
#6130000000
0#
0)
#6140000000
1#
0%
1&
1)
0+
1,
#6150000000
0#
0)
#6160000000
1#
1%
0&
1)
1+
0,
#6170000000
0#
0)
#6180000000
1#
0%
1&
1)
0+
1,
#6190000000
0#
0)
#6200000000
1#
1%
0&
1)
1+
0,
#6210000000
0#
0)
#6220000000
1#
0%
1&
1)
0+
1,
#6230000000
0#
0)
#6240000000
1#
1%
0&
1)
1+
0,
#6250000000
0#
0)
#6260000000
1#
0%
1&
1)
0+
1,
#6270000000
0#
0)
#6280000000
1#
1%
0&
1)
1+
0,
#6290000000
0#
0)
#6300000000
1#
0%
1&
1)
0+
1,
#6310000000
0#
0)
#6320000000
1#
1%
0&
1)
1+
0,
#6330000000
0#
0)
#6340000000
1#
0%
1&
1)
0+
1,
#6350000000
0#
0)
#6360000000
1#
1%
0&
1)
1+
0,
#6370000000
0#
0)
#6380000000
1#
0%
1&
1)
0+
1,
#6390000000
0#
0)
#6400000000
1#
1%
0&
1)
1+
0,
#6410000000
0#
0)
#6420000000
1#
0%
1&
1)
0+
1,
#6430000000
0#
0)
#6440000000
1#
1%
0&
1)
1+
0,
#6450000000
0#
0)
#6460000000
1#
0%
1&
1)
0+
1,
#6470000000
0#
0)
#6480000000
1#
1%
0&
1)
1+
0,
#6490000000
0#
0)
#6500000000
1#
0%
1&
1)
0+
1,
#6510000000
0#
0)
#6520000000
1#
1%
0&
1)
1+
0,
#6530000000
0#
0)
#6540000000
1#
0%
1&
1)
0+
1,
#6550000000
0#
0)
#6560000000
1#
1%
0&
1)
1+
0,
#6570000000
0#
0)
#6580000000
1#
0%
1&
1)
0+
1,
#6590000000
0#
0)
#6600000000
1#
1%
0&
1)
1+
0,
#6610000000
0#
0)
#6620000000
1#
0%
1&
1)
0+
1,
#6630000000
0#
0)
#6640000000
1#
1%
0&
1)
1+
0,
#6650000000
0#
0)
#6660000000
1#
0%
1&
1)
0+
1,
#6670000000
0#
0)
#6680000000
1#
1%
0&
1)
1+
0,
#6690000000
0#
0)
#6700000000
1#
0%
1&
1)
0+
1,
#6710000000
0#
0)
#6720000000
1#
1%
0&
1)
1+
0,
#6730000000
0#
0)
#6740000000
1#
0%
1&
1)
0+
1,
#6750000000
0#
0)
#6760000000
1#
1%
0&
1)
1+
0,
#6770000000
0#
0)
#6780000000
1#
0%
1&
1)
0+
1,
#6790000000
0#
0)
#6800000000
1#
1%
0&
1)
1+
0,
#6810000000
0#
0)
#6820000000
1#
0%
1&
1)
0+
1,
#6830000000
0#
0)
#6840000000
1#
1%
0&
1)
1+
0,
#6850000000
0#
0)
#6860000000
1#
0%
1&
1)
0+
1,
#6870000000
0#
0)
#6880000000
1#
1%
0&
1)
1+
0,
#6890000000
0#
0)
#6900000000
1#
0%
1&
1)
0+
1,
#6910000000
0#
0)
#6920000000
1#
1%
0&
1)
1+
0,
#6930000000
0#
0)
#6940000000
1#
0%
1&
1)
0+
1,
#6950000000
0#
0)
#6960000000
1#
1%
0&
1)
1+
0,
#6970000000
0#
0)
#6980000000
1#
0%
1&
1)
0+
1,
#6990000000
0#
0)
#7000000000
1#
1%
0&
1)
1+
0,
#7010000000
0#
0)
#7020000000
1#
0%
1&
1)
0+
1,
#7030000000
0#
0)
#7040000000
1#
1%
0&
1)
1+
0,
#7050000000
0#
0)
#7060000000
1#
0%
1&
1)
0+
1,
#7070000000
0#
0)
#7080000000
1#
1%
0&
1)
1+
0,
#7090000000
0#
0)
#7100000000
1#
0%
1&
1)
0+
1,
#7110000000
0#
0)
#7120000000
1#
1%
0&
1)
1+
0,
#7130000000
0#
0)
#7140000000
1#
0%
1&
1)
0+
1,
#7150000000
0#
0)
#7160000000
1#
1%
0&
1)
1+
0,
#7170000000
0#
0)
#7180000000
1#
0%
1&
1)
0+
1,
#7190000000
0#
0)
#7200000000
1#
1%
0&
1)
1+
0,
#7210000000
0#
0)
#7220000000
1#
0%
1&
1)
0+
1,
#7230000000
0#
0)
#7240000000
1#
1%
0&
1)
1+
0,
#7250000000
0#
0)
#7260000000
1#
0%
1&
1)
0+
1,
#7270000000
0#
0)
#7280000000
1#
1%
0&
1)
1+
0,
#7290000000
0#
0)
#7300000000
1#
0%
1&
1)
0+
1,
#7310000000
0#
0)
#7320000000
1#
1%
0&
1)
1+
0,
#7330000000
0#
0)
#7340000000
1#
0%
1&
1)
0+
1,
#7350000000
0#
0)
#7360000000
1#
1%
0&
1)
1+
0,
#7370000000
0#
0)
