lcm/lcm.vhdl
-- library  ieee;
-- use ieee.std_logic_1164.all;

-- entity lcm is
-- 	port(rst, clk : in std_logic;
-- 	    a, b : in integer;
-- 	    LCM : out integer);
-- end lcm;

-- architecture lcm_arch of lcm is
-- type state is (start, input, output, check, check1,update_x,  update_y);
-- signal current_state, next_state: state;
-- begin
-- state_reg:Process(clk, rst)
-- BEGIN
-- 	IF(rst = '1') THEN
-- 		current_state <= start;
-- 	ELSIF(rising_edge(clk)) THEN
-- 		current_state <= next_state;
-- 	END IF;
-- end process;
-- compute:Process(a, b, current_state)
-- variable  z, x, y, r, p : integer;
-- begin
-- 	case current_state IS 
-- 		WHEN start =>
-- 			next_state <= input;
-- 		WHEN input =>
-- 			x:= a;
-- 			y:= b;
-- 			z := x * y;
-- 			next_state <= check;
-- 		WHEN check =>
-- 			if(x< y) THEN
-- 				next_state <= update_x;
-- 			else
-- 				next_state <= update_y;
-- 			END IF;
-- 			next_state <= check1;
-- 		WHEN  check1 =>
-- 			while y /= 0 loop
-- 				r:= x mod y;
-- 				x:= y;
-- 				y:= r;
-- 			end loop;
-- 			next_state <= output;
-- 		WHEN update_x =>
-- 			p:=x;
-- 			x:=y;
-- 			y:=p;
-- 		when update_y =>
-- 			x:=x;
-- 			y:=y;
-- 		WHEN output =>
-- 			LCM <= z / x;	
-- 			next_state <= start;
-- 		WHEN others =>
-- 			next_state <= start;
-- 	end case;
-- end process compute;
-- end lcm_arch;

library ieee;
use ieee.std_logic_1164.all;

entity my_lcm is
    port (
        rst, clk : in std_logic;
        input_a, input_b : in integer;
        lcm_result : out integer
    );
end my_lcm;

architecture lcm_arch of my_lcm is
    type state is (start, input, output, check, check1, update_x, update_y);
    signal current_state, next_state: state;
begin
    state_reg: process(clk, rst)
    begin
        if rst = '1' then
            current_state <= start;
        elsif rising_edge(clk) then
            current_state <= next_state;
        end if;
    end process state_reg;

    compute: process(input_a, input_b, current_state)
        variable z, x, y, r, p : integer;
    begin
        case current_state is 
            when start =>
                next_state <= input;
            when input =>
                x := input_a;
                y := input_b;
                z := x * y;
                next_state <= check;
            when check =>
                if x < y then
                    next_state <= update_x;
                else
                    next_state <= update_y;
                end if;
                next_state <= check1;
            when check1 =>
                while y /= 0 loop
                    r := x mod y;
                    x := y;
                    y := r;
                end loop;
                next_state <= output;
            when update_x =>
                p := x;
                x := y;
                y := p;
            when update_y =>
                x := x;
                y := y;
            when output =>
                lcm_result <= z / x;
                next_state <= start;
            when others =>
                next_state <= start;
        end case;
    end process compute;
end lcm_arch;

lcm/lcmTB.vhdl
LIBRARY ieee;
USE ieee.std_logic_1164.ALL;

ENTITY my_lcm_tb IS
END my_lcm_tb;

ARCHITECTURE tb_arch OF my_lcm_tb IS
    COMPONENT my_lcm IS
        PORT (
            rst, clk : IN STD_LOGIC;
            input_a, input_b : IN INTEGER;
            lcm_result : OUT INTEGER
        );
    END COMPONENT my_lcm;

    SIGNAL rst_tb, clk_tb : STD_LOGIC := '0';
    SIGNAL input_a_tb, input_b_tb, lcm_result_tb : INTEGER := 0;
BEGIN
    dut : my_lcm PORT MAP(rst => rst_tb, clk => clk_tb, input_a => input_a_tb, input_b => input_b_tb, lcm_result => lcm_result_tb);

    clock : PROCESS
    BEGIN
        clk_tb <= '1';
        WAIT FOR 100 ns;

        clk_tb <= '0';
        WAIT FOR 100 ns;

    END PROCESS;
    stimulus_proc : PROCESS
    BEGIN
        rst_tb <= '1';
        WAIT FOR 100 ns;
        rst_tb <= '0';
        WAIT FOR 100 ns;

        input_a_tb <= 10; -- Change input values as needed
        input_b_tb <= 15;
        WAIT FOR 1000 ns;

        input_a_tb <= 6789;
        input_b_tb <= 666;
        WAIT FOR 1000 ns;

        input_a_tb <= 50;
        input_b_tb <= 100;
        WAIT FOR 1000 ns;

        -- Add more test cases or stimulus here

        WAIT;
    END PROCESS;
END tb_arch;

lcm/result.vcd
$date
  Sat Feb 10 14:15:51 2024
$end
$version
  GHDL v0
$end
$timescale
  1 fs
$end
$scope module standard $end
$upscope $end
$scope module std_logic_1164 $end
$upscope $end
$scope module my_lcm_tb $end
$var reg 1 ! rst_tb $end
$var reg 1 " clk_tb $end
$var integer 32 # input_a_tb $end
$var integer 32 $ input_b_tb $end
$var integer 32 % lcm_result_tb $end
$scope module dut $end
$var reg 1 & rst $end
$var reg 1 ' clk $end
$var integer 32 ( input_a $end
$var integer 32 ) input_b $end
$var integer 32 * lcm_result $end
$comment current_state is not handled $end
$comment next_state is not handled $end
$upscope $end
$upscope $end
$enddefinitions $end
#0
1!
1"
b0 #
b0 $
b10000000000000000000000000000000 %
1&
1'
b0 (
b0 )
b10000000000000000000000000000000 *
#100000000
0!
0"
0&
0'
#200000000
1"
b1010 #
b1111 $
1'
b1010 (
b1111 )
#300000000
0"
0'
#400000000
1"
1'
#500000000
0"
0'
#600000000
1"
1'
#700000000
0"
0'
#800000000
1"
b11110 %
1'
b11110 *
#900000000
0"
0'
#1000000000
1"
1'
#1100000000
0"
0'
#1200000000
1"
b1101010000101 #
b1010011010 $
1'
b1101010000101 (
b1010011010 )
#1300000000
0"
0'
#1400000000
1"
1'
#1500000000
0"
0'
#1600000000
1"
1'
#1700000000
0"
0'
#1800000000
1"
b101101111111101010110 %
1'
b101101111111101010110 *
#1900000000
0"
0'
#2000000000
1"
1'
#2100000000
0"
0'
#2200000000
1"
b110010 #
b1100100 $
1'
b110010 (
b1100100 )
#2300000000
0"
0'
#2400000000
1"
1'
#2500000000
0"
0'
#2600000000
1"
1'
#2700000000
0"
0'
#2800000000
1"
b1100100 %
1'
b1100100 *
