upCounter/upcounter.vhdl
LIBRARY IEEE;
USE IEEE.STD_LOGIC_1164.ALL;

ENTITY T_flipflop
    IS
    PORT (
        T, CLK, RST : IN STD_LOGIC;
        Q : OUT STD_LOGIC);
END T_flipflop
;

ARCHITECTURE T_flipflop
    OF T_flipflop
    IS
    SIGNAL Q_temp : STD_LOGIC;
BEGIN
    PROCESS (CLK, RST)
    BEGIN
        IF RST = '1' THEN
            Q_temp <= '0';
        ELSIF rising_edge(CLK) THEN
            IF T = '1' THEN
                Q_temp <= NOT Q_temp;
            ELSE
                Q_temp <= Q_temp;
            END IF;
        END IF;
    END PROCESS;

    Q <= Q_temp;
END T_flipflop
;

LIBRARY IEEE;
USE IEEE.STD_LOGIC_1164.ALL;

ENTITY AND_G IS
    PORT (
        A, B : IN STD_LOGIC;
        Z : OUT STD_LOGIC);
END AND_G;

ARCHITECTURE AND_G OF AND_G IS
BEGIN
    Z <= A AND B;

END AND_G;

LIBRARY IEEE;
USE IEEE.STD_LOGIC_1164.ALL;

ENTITY up_counter IS
    PORT (
        CLK, RST : IN STD_LOGIC;
        Q : OUT STD_LOGIC_VECTOR(2 DOWNTO 0));
END up_counter;

ARCHITECTURE up_counter OF up_counter IS
    COMPONENT AND_G IS
        PORT (
            A, B : IN STD_LOGIC;
            Z : OUT STD_LOGIC);
    END COMPONENT AND_G;

    COMPONENT T_flipflop
        IS
        PORT (
            T, CLK, RST : IN STD_LOGIC;
            Q : OUT STD_LOGIC);
    END COMPONENT T_flipflop
    ;
    SIGNAL QA, QB, QC, TC : STD_LOGIC;

BEGIN
    T1 : T_flipflop
    PORT MAP(T => '1', CLK => CLK, RST => RST, Q => QA);
    T2 : T_flipflop
    PORT MAP(T => QA, CLK => CLK, RST => RST, Q => QB);
    A1 : AND_G PORT MAP(A => QA, B => QB, Z => TC);
    T3 : T_flipflop
    PORT MAP(T => TC, CLK => CLK, RST => RST, Q => Q(2));
    Q(0) <= '1' WHEN QA = '1' ELSE
    '0';
    Q(1) <= '1' WHEN QB = '1' ELSE
    '0';

END up_counter;

ES-assignment/upCounter/upcounterTB.vhdl
LIBRARY IEEE;
USE IEEE.STD_LOGIC_1164.ALL;

ENTITY counter_tb IS
END counter_tb;

ARCHITECTURE counter_tb OF counter_tb IS
	COMPONENT up_counter IS
		PORT (
			CLK, RST : IN STD_LOGIC;
			Q : OUT STD_LOGIC_VECTOR(2 DOWNTO 0));
	END COMPONENT up_counter;

	SIGNAL CLK, RST : STD_LOGIC := '0';
	SIGNAL Q : STD_LOGIC_VECTOR(2 DOWNTO 0);

BEGIN
	counter1 : up_counter PORT MAP(CLK => CLK, RST => RST, Q => Q);
	PROCESS
	BEGIN
		CLK <= '0';
		WAIT FOR 5 ns;
		CLK <= '1';
		WAIT FOR 5 ns;
	END PROCESS;

	PROCESS
	BEGIN
		RST <= '1';
		WAIT FOR 10 ns;
		RST <= '0';
		WAIT FOR 80 ns;
	END PROCESS;

END counter_tb;

upCounter/result.vcd
$date
  Sun Feb 18 16:13:39 2024
$end
$version
  GHDL v0
$end
$timescale
  1 fs
$end
$scope module standard $end
$upscope $end
$scope module std_logic_1164 $end
$upscope $end
$scope module counter_tb $end
$var reg 1 ! clk $end
$var reg 1 " rst $end
$var reg 3 # q[2:0] $end
$scope module counter1 $end
$var reg 1 $ clk $end
$var reg 1 % rst $end
$var reg 3 & q[2:0] $end
$var reg 1 ' qa $end
$var reg 1 ( qb $end
$var reg 1 ) qc $end
$var reg 1 * tc $end
$scope module t1 $end
$var reg 1 + t $end
$var reg 1 , clk $end
$var reg 1 - rst $end
$var reg 1 . q $end
$var reg 1 / q_temp $end
$upscope $end
$scope module t2 $end
$var reg 1 0 t $end
$var reg 1 1 clk $end
$var reg 1 2 rst $end
$var reg 1 3 q $end
$var reg 1 4 q_temp $end
$upscope $end
$scope module a1 $end
$var reg 1 5 a $end
$var reg 1 6 b $end
$var reg 1 7 z $end
$upscope $end
$scope module t3 $end
$var reg 1 8 t $end
$var reg 1 9 clk $end
$var reg 1 : rst $end
$var reg 1 ; q $end
$var reg 1 < q_temp $end
$upscope $end
$upscope $end
$upscope $end
$enddefinitions $end
#0
0!
1"
b000 #
0$
1%
b000 &
0'
0(
U)
0*
1+
0,
1-
0.
0/
00
01
12
03
04
05
06
07
08
09
1:
0;
0<
#5000000
1!
1$
1,
11
19
#10000000
0!
0"
0$
0%
0,
0-
01
02
09
0:
#15000000
1!
b001 #
1$
b001 &
1'
1,
1.
1/
10
11
15
19
#20000000
0!
0$
0,
01
09
#25000000
1!
b010 #
1$
b010 &
0'
1(
1,
0.
0/
00
11
13
14
05
16
19
#30000000
0!
0$
0,
01
09
#35000000
1!
b011 #
1$
b011 &
1'
1*
1,
1.
1/
10
11
15
17
18
19
#40000000
0!
0$
0,
01
09
#45000000
1!
b100 #
1$
b100 &
0'
0(
0*
1,
0.
0/
00
11
03
04
05
06
07
08
19
1;
1<
#50000000
0!
0$
0,
01
09
#55000000
1!
b101 #
1$
b101 &
1'
1,
1.
1/
10
11
15
19
#60000000
0!
0$
0,
01
09
#65000000
1!
b110 #
1$
b110 &
0'
1(
1,
0.
0/
00
11
13
14
05
16
19
#70000000
0!
0$
0,
01
09
#75000000
1!
b111 #
1$
b111 &
1'
1*
1,
1.
1/
10
11
15
17
18
19
#80000000
0!
0$
0,
01
09
#85000000
1!
b000 #
1$
b000 &
0'
0(
0*
1,
0.
0/
00
11
03
04
05
06
07
08
19
0;
0<
#90000000
0!
1"
0$
1%
0,
1-
01
12
09
1:
#95000000
1!
1$
1,
11
19
#100000000
0!
0"
0$
0%
0,
0-
01
02
09
0:
#105000000
1!
b001 #
1$
b001 &
1'
1,
1.
1/
10
11
15
19
#110000000
0!
0$
0,
01
09
#115000000
1!
b010 #
1$
b010 &
0'
1(
1,
0.
0/
00
11
13
14
05
16
19
#120000000
0!
0$
0,
01
09
#125000000
1!
b011 #
1$
b011 &
1'
1*
1,
1.
1/
10
11
15
17
18
19
#130000000
0!
0$
0,
01
09
#135000000
1!
b100 #
1$
b100 &
0'
0(
0*
1,
0.
0/
00
11
03
04
05
06
07
08
19
1;
1<
#140000000
0!
0$
0,
01
09
#145000000
1!
b101 #
1$
b101 &
1'
1,
1.
1/
10
11
15
19
#150000000
0!
0$
0,
01
09
#155000000
1!
b110 #
1$
b110 &
0'
1(
1,
0.
0/
00
11
13
14
05
16
19
#160000000
0!
0$
0,
01
09
#165000000
1!
b111 #
1$
b111 &
1'
1*
1,
1.
1/
10
11
15
17
18
19
#170000000
0!
0$
0,
01
09
#175000000
1!
b000 #
1$
b000 &
0'
0(
0*
1,
0.
0/
00
11
03
04
05
06
07
08
19
0;
0<
#180000000
0!
1"
0$
1%
0,
1-
01
12
09
1:
#185000000
1!
1$
1,
11
19
#190000000
0!
0"
0$
0%
0,
0-
01
02
09
0:
#195000000
1!
b001 #
1$
b001 &
1'
1,
1.
1/
10
11
15
19
#200000000
0!
0$
0,
01
09
#205000000
1!
b010 #
1$
b010 &
0'
1(
1,
0.
0/
00
11
13
14
05
16
19
#210000000
0!
0$
0,
01
09
#215000000
1!
b011 #
1$
b011 &
1'
1*
1,
1.
1/
10
11
15
17
18
19
#220000000
0!
0$
0,
01
09
#225000000
1!
b100 #
1$
b100 &
0'
0(
0*
1,
0.
0/
00
11
03
04
05
06
07
08
19
1;
1<
#230000000
0!
0$
0,
01
09
#235000000
1!
b101 #
1$
b101 &
1'
1,
1.
1/
10
11
15
19
#240000000
0!
0$
0,
01
09
#245000000
1!
b110 #
1$
b110 &
0'
1(
1,
0.
0/
00
11
13
14
05
16
19
#250000000
0!
0$
0,
01
09
#255000000
1!
b111 #
1$
b111 &
1'
1*
1,
1.
1/
10
11
15
17
18
19
#260000000
0!
0$
0,
01
09
#265000000
1!
b000 #
1$
b000 &
0'
0(
0*
1,
0.
0/
00
11
03
04
05
06
07
08
19
0;
0<
#270000000
0!
1"
0$
1%
0,
1-
01
12
09
1:
#275000000
1!
1$
1,
11
19
#280000000
0!
0"
0$
0%
0,
0-
01
02
09
0:
#285000000
1!
b001 #
1$
b001 &
1'
1,
1.
1/
10
11
15
19
#290000000
0!
0$
0,
01
09
#295000000
1!
b010 #
1$
b010 &
0'
1(
1,
0.
0/
00
11
13
14
05
16
19
#300000000
0!
0$
0,
01
09
#305000000
1!
b011 #
1$
b011 &
1'
1*
1,
1.
1/
10
11
15
17
18
19
#310000000
0!
0$
0,
01
09
#315000000
1!
b100 #
1$
b100 &
0'
0(
0*
1,
0.
0/
00
11
03
04
05
06
07
08
19
1;
1<
#320000000
0!
0$
0,
01
09
#325000000
1!
b101 #
1$
b101 &
1'
1,
1.
1/
10
11
15
19
#330000000
0!
0$
0,
01
09
#335000000
1!
b110 #
1$
b110 &
0'
1(
1,
0.
0/
00
11
13
14
05
16
19
#340000000
0!
0$
0,
01
09
#345000000
1!
b111 #
1$
b111 &
1'
1*
1,
1.
1/
10
11
15
17
18
19
#350000000
0!
0$
0,
01
09
#355000000
1!
b000 #
1$
b000 &
0'
0(
0*
1,
0.
0/
00
11
03
04
05
06
07
08
19
0;
0<
#360000000
0!
1"
0$
1%
0,
1-
01
12
09
1:
#365000000
1!
1$
1,
11
19
#370000000
0!
0"
0$
0%
0,
0-
01
02
09
0:
#375000000
1!
b001 #
1$
b001 &
1'
1,
1.
1/
10
11
15
19
#380000000
0!
0$
0,
01
09
#385000000
1!
b010 #
1$
b010 &
0'
1(
1,
0.
0/
00
11
13
14
05
16
19
#390000000
0!
0$
0,
01
09
#395000000
1!
b011 #
1$
b011 &
1'
1*
1,
1.
1/
10
11
15
17
18
19
#400000000
0!
0$
0,
01
09
#405000000
1!
b100 #
1$
b100 &
0'
0(
0*
1,
0.
0/
00
11
03
04
05
06
07
08
19
1;
1<
#410000000
0!
0$
0,
01
09
#415000000
1!
b101 #
1$
b101 &
1'
1,
1.
1/
10
11
15
19
#420000000
0!
0$
0,
01
09
#425000000
1!
b110 #
1$
b110 &
0'
1(
1,
0.
0/
00
11
13
14
05
16
19
#430000000
0!
0$
0,
01
09
#435000000
1!
b111 #
1$
b111 &
1'
1*
1,
1.
1/
10
11
15
17
18
19
#440000000
0!
0$
0,
01
09
#445000000
1!
b000 #
1$
b000 &
0'
0(
0*
1,
0.
0/
00
11
03
04
05
06
07
08
19
0;
0<
#450000000
0!
1"
0$
1%
0,
1-
01
12
09
1:
#455000000
1!
1$
1,
11
19
#460000000
0!
0"
0$
0%
0,
0-
01
02
09
0:
#465000000
1!
b001 #
1$
b001 &
1'
1,
1.
1/
10
11
15
19
#470000000
0!
0$
0,
01
09
#475000000
1!
b010 #
1$
b010 &
0'
1(
1,
0.
0/
00
11
13
14
05
16
19
#480000000
0!
0$
0,
01
09
#485000000
1!
b011 #
1$
b011 &
1'
1*
1,
1.
1/
10
11
15
17
18
19
#490000000
0!
0$
0,
01
09
#495000000
1!
b100 #
1$
b100 &
0'
0(
0*
1,
0.
0/
00
11
03
04
05
06
07
08
19
1;
1<
#500000000
0!
0$
0,
01
09
#505000000
1!
b101 #
1$
b101 &
1'
1,
1.
1/
10
11
15
19
#510000000
0!
0$
0,
01
09
#515000000
1!
b110 #
1$
b110 &
0'
1(
1,
0.
0/
00
11
13
14
05
16
19
#520000000
0!
0$
0,
01
09
#525000000
1!
b111 #
1$
b111 &
1'
1*
1,
1.
1/
10
11
15
17
18
19
#530000000
0!
0$
0,
01
09
#535000000
1!
b000 #
1$
b000 &
0'
0(
0*
1,
0.
0/
00
11
03
04
05
06
07
08
19
0;
0<
#540000000
0!
1"
0$
1%
0,
1-
01
12
09
1:
#545000000
1!
1$
1,
11
19
#550000000
0!
0"
0$
0%
0,
0-
01
02
09
0:
#555000000
1!
b001 #
1$
b001 &
1'
1,
1.
1/
10
11
15
19
#560000000
0!
0$
0,
01
09
#565000000
1!
b010 #
1$
b010 &
0'
1(
1,
0.
0/
00
11
13
14
05
16
19
#570000000
0!
0$
0,
01
09
#575000000
1!
b011 #
1$
b011 &
1'
1*
1,
1.
1/
10
11
15
17
18
19
#580000000
0!
0$
0,
01
09
#585000000
1!
b100 #
1$
b100 &
0'
0(
0*
1,
0.
0/
00
11
03
04
05
06
07
08
19
1;
1<
#590000000
0!
0$
0,
01
09
#595000000
1!
b101 #
1$
b101 &
1'
1,
1.
1/
10
11
15
19
#600000000
0!
0$
0,
01
09
#605000000
1!
b110 #
1$
b110 &
0'
1(
1,
0.
0/
00
11
13
14
05
16
19
#610000000
0!
0$
0,
01
09
#615000000
1!
b111 #
1$
b111 &
1'
1*
1,
1.
1/
10
11
15
17
18
19
#620000000
0!
0$
0,
01
09
#625000000
1!
b000 #
1$
b000 &
0'
0(
0*
1,
0.
0/
00
11
03
04
05
06
07
08
19
0;
0<
#630000000
0!
1"
0$
1%
0,
1-
01
12
09
1:
#635000000
1!
1$
1,
11
19
#640000000
0!
0"
0$
0%
0,
0-
01
02
09
0:
#645000000
1!
b001 #
1$
b001 &
1'
1,
1.
1/
10
11
15
19
#650000000
0!
0$
0,
01
09
#655000000
1!
b010 #
1$
b010 &
0'
1(
1,
0.
0/
00
11
13
14
05
16
19
#660000000
0!
0$
0,
01
09
#665000000
1!
b011 #
1$
b011 &
1'
1*
1,
1.
1/
10
11
15
17
18
19
#670000000
0!
0$
0,
01
09
#675000000
1!
b100 #
1$
b100 &
0'
0(
0*
1,
0.
0/
00
11
03
04
05
06
07
08
19
1;
1<
#680000000
0!
0$
0,
01
09
#685000000
1!
b101 #
1$
b101 &
1'
1,
1.
1/
10
11
15
19
#690000000
0!
0$
0,
01
09
#695000000
1!
b110 #
1$
b110 &
0'
1(
1,
0.
0/
00
11
13
14
05
16
19
#700000000
0!
0$
0,
01
09
#705000000
1!
b111 #
1$
b111 &
1'
1*
1,
1.
1/
10
11
15
17
18
19
#710000000
0!
0$
0,
01
09
#715000000
1!
b000 #
1$
b000 &
0'
0(
0*
1,
0.
0/
00
11
03
04
05
06
07
08
19
0;
0<
#720000000
0!
1"
0$
1%
0,
1-
01
12
09
1:
#725000000
1!
1$
1,
11
19
#730000000
0!
0"
0$
0%
0,
0-
01
02
09
0:
#735000000
1!
b001 #
1$
b001 &
1'
1,
1.
1/
10
11
15
19
#740000000
0!
0$
0,
01
09
#745000000
1!
b010 #
1$
b010 &
0'
1(
1,
0.
0/
00
11
13
14
05
16
19
#750000000
0!
0$
0,
01
09
#755000000
1!
b011 #
1$
b011 &
1'
1*
1,
1.
1/
10
11
15
17
18
19
#760000000
0!
0$
0,
01
09
#765000000
1!
b100 #
1$
b100 &
0'
0(
0*
1,
0.
0/
00
11
03
04
05
06
07
08
19
1;
1<
#770000000
0!
0$
0,
01
09
#775000000
1!
b101 #
1$
b101 &
1'
1,
1.
1/
10
11
15
19
#780000000
0!
0$
0,
01
09
#785000000
1!
b110 #
1$
b110 &
0'
1(
1,
0.
0/
00
11
13
14
05
16
19
#790000000
0!
0$
0,
01
09
#795000000
1!
b111 #
1$
b111 &
1'
1*
1,
1.
1/
10
11
15
17
18
19
#800000000
0!
0$
0,
01
09
#805000000
1!
b000 #
1$
b000 &
0'
0(
0*
1,
0.
0/
00
11
03
04
05
06
07
08
19
0;
0<
#810000000
0!
1"
0$
1%
0,
1-
01
12
09
1:
#815000000
1!
1$
1,
11
19
#820000000
0!
0"
0$
0%
0,
0-
01
02
09
0:
#825000000
1!
b001 #
1$
b001 &
1'
1,
1.
1/
10
11
15
19
#830000000
0!
0$
0,
01
09
#835000000
1!
b010 #
1$
b010 &
0'
1(
1,
0.
0/
00
11
13
14
05
16
19
#840000000
0!
0$
0,
01
09
#845000000
1!
b011 #
1$
b011 &
1'
1*
1,
1.
1/
10
11
15
17
18
19
#850000000
0!
0$
0,
01
09
#855000000
1!
b100 #
1$
b100 &
0'
0(
0*
1,
0.
0/
00
11
03
04
05
06
07
08
19
1;
1<
#860000000
0!
0$
0,
01
09
#865000000
1!
b101 #
1$
b101 &
1'
1,
1.
1/
10
11
15
19
#870000000
0!
0$
0,
01
09
#875000000
1!
b110 #
1$
b110 &
0'
1(
1,
0.
0/
00
11
13
14
05
16
19
#880000000
0!
0$
0,
01
09
#885000000
1!
b111 #
1$
b111 &
1'
1*
1,
1.
1/
10
11
15
17
18
19
#890000000
0!
0$
0,
01
09
#895000000
1!
b000 #
1$
b000 &
0'
0(
0*
1,
0.
0/
00
11
03
04
05
06
07
08
19
0;
0<
#900000000
0!
1"
0$
1%
0,
1-
01
12
09
1:
#905000000
1!
1$
1,
11
19
#910000000
0!
0"
0$
0%
0,
0-
01
02
09
0:
#915000000
1!
b001 #
1$
b001 &
1'
1,
1.
1/
10
11
15
19
#920000000
0!
0$
0,
01
09
#925000000
1!
b010 #
1$
b010 &
0'
1(
1,
0.
0/
00
11
13
14
05
16
19
#930000000
0!
0$
0,
01
09
#935000000
1!
b011 #
1$
b011 &
1'
1*
1,
1.
1/
10
11
15
17
18
19
#940000000
0!
0$
0,
01
09
#945000000
1!
b100 #
1$
b100 &
0'
0(
0*
1,
0.
0/
00
11
03
04
05
06
07
08
19
1;
1<
#950000000
0!
0$
0,
01
09
#955000000
1!
b101 #
1$
b101 &
1'
1,
1.
1/
10
11
15
19
#960000000
0!
0$
0,
01
09
#965000000
1!
b110 #
1$
b110 &
0'
1(
1,
0.
0/
00
11
13
14
05
16
19
#970000000
0!
0$
0,
01
09
#975000000
1!
b111 #
1$
b111 &
1'
1*
1,
1.
1/
10
11
15
17
18
19
#980000000
0!
0$
0,
01
09
#985000000
1!
b000 #
1$
b000 &
0'
0(
0*
1,
0.
0/
00
11
03
04
05
06
07
08
19
0;
0<
#990000000
0!
1"
0$
1%
0,
1-
01
12
09
1:
#995000000
1!
1$
1,
11
19
#1000000000
0!
0"
0$
0%
0,
0-
01
02
09
0:
#1005000000
1!
b001 #
1$
b001 &
1'
1,
1.
1/
10
11
15
19
#1010000000
0!
0$
0,
01
09
#1015000000
1!
b010 #
1$
b010 &
0'
1(
1,
0.
0/
00
11
13
14
05
16
19
#1020000000
0!
0$
0,
01
09
#1025000000
1!
b011 #
1$
b011 &
1'
1*
1,
1.
1/
10
11
15
17
18
19
#1030000000
0!
0$
0,
01
09
#1035000000
1!
b100 #
1$
b100 &
0'
0(
0*
1,
0.
0/
00
11
03
04
05
06
07
08
19
1;
1<
#1040000000
0!
0$
0,
01
09
#1045000000
1!
b101 #
1$
b101 &
1'
1,
1.
1/
10
11
15
19
#1050000000
0!
0$
0,
01
09
#1055000000
1!
b110 #
1$
b110 &
0'
1(
1,
0.
0/
00
11
13
14
05
16
19
#1060000000
0!
0$
0,
01
09
#1065000000
1!
b111 #
1$
b111 &
1'
1*
1,
1.
1/
10
11
15
17
18
19
#1070000000
0!
0$
0,
01
09
#1075000000
1!
b000 #
1$
b000 &
0'
0(
0*
1,
0.
0/
00
11
03
04
05
06
07
08
19
0;
0<
#1080000000
0!
1"
0$
1%
0,
1-
01
12
09
1:
#1085000000
1!
1$
1,
11
19
#1090000000
0!
0"
0$
0%
0,
0-
01
02
09
0:
#1095000000
1!
b001 #
1$
b001 &
1'
1,
1.
1/
10
11
15
19
#1100000000
0!
0$
0,
01
09
#1105000000
1!
b010 #
1$
b010 &
0'
1(
1,
0.
0/
00
11
13
14
05
16
19
#1110000000
0!
0$
0,
01
09
#1115000000
1!
b011 #
1$
b011 &
1'
1*
1,
1.
1/
10
11
15
17
18
19
#1120000000
0!
0$
0,
01
09
#1125000000
1!
b100 #
1$
b100 &
0'
0(
0*
1,
0.
0/
00
11
03
04
05
06
07
08
19
1;
1<
#1130000000
0!
0$
0,
01
09
#1135000000
1!
b101 #
1$
b101 &
1'
1,
1.
1/
10
11
15
19
#1140000000
0!
0$
0,
01
09
#1145000000
1!
b110 #
1$
b110 &
0'
1(
1,
0.
0/
00
11
13
14
05
16
19
#1150000000
0!
0$
0,
01
09
#1155000000
1!
b111 #
1$
b111 &
1'
1*
1,
1.
1/
10
11
15
17
18
19
#1160000000
0!
0$
0,
01
09
#1165000000
1!
b000 #
1$
b000 &
0'
0(
0*
1,
0.
0/
00
11
03
04
05
06
07
08
19
0;
0<
#1170000000
0!
1"
0$
1%
0,
1-
01
12
09
1:
#1175000000
1!
1$
1,
11
19
#1180000000
0!
0"
0$
0%
0,
0-
01
02
09
0:
#1185000000
1!
b001 #
1$
b001 &
1'
1,
1.
1/
10
11
15
19
#1190000000
0!
0$
0,
01
09
#1195000000
1!
b010 #
1$
b010 &
0'
1(
1,
0.
0/
00
11
13
14
05
16
19
#1200000000
0!
0$
0,
01
09
#1205000000
1!
b011 #
1$
b011 &
1'
1*
1,
1.
1/
10
11
15
17
18
19
#1210000000
0!
0$
0,
01
09
#1215000000
1!
b100 #
1$
b100 &
0'
0(
0*
1,
0.
0/
00
11
03
04
05
06
07
08
19
1;
1<
#1220000000
0!
0$
0,
01
09
#1225000000
1!
b101 #
1$
b101 &
1'
1,
1.
1/
10
11
15
19
#1230000000
0!
0$
0,
01
09
#1235000000
1!
b110 #
1$
b110 &
0'
1(
1,
0.
0/
00
11
13
14
05
16
19
#1240000000
0!
0$
0,
01
09
#1245000000
1!
b111 #
1$
b111 &
1'
1*
1,
1.
1/
10
11
15
17
18
19
#1250000000
0!
0$
0,
01
09
#1255000000
1!
b000 #
1$
b000 &
0'
0(
0*
1,
0.
0/
00
11
03
04
05
06
07
08
19
0;
0<
#1260000000
0!
1"
0$
1%
0,
1-
01
12
09
1:
#1265000000
1!
1$
1,
11
19
#1270000000
0!
0"
0$
0%
0,
0-
01
02
09
0:
#1275000000
1!
b001 #
1$
b001 &
1'
1,
1.
1/
10
11
15
19
#1280000000
0!
0$
0,
01
09
#1285000000
1!
b010 #
1$
b010 &
0'
1(
1,
0.
0/
00
11
13
14
05
16
19
#1290000000
0!
0$
0,
01
09
#1295000000
1!
b011 #
1$
b011 &
1'
1*
1,
1.
1/
10
11
15
17
18
19
#1300000000
0!
0$
0,
01
09
#1305000000
1!
b100 #
1$
b100 &
0'
0(
0*
1,
0.
0/
00
11
03
04
05
06
07
08
19
1;
1<
#1310000000
0!
0$
0,
01
09
#1315000000
1!
b101 #
1$
b101 &
1'
1,
1.
1/
10
11
15
19
#1320000000
0!
0$
0,
01
09
#1325000000
1!
b110 #
1$
b110 &
0'
1(
1,
0.
0/
00
11
13
14
05
16
19
#1330000000
0!
0$
0,
01
09
#1335000000
1!
b111 #
1$
b111 &
1'
1*
1,
1.
1/
10
11
15
17
18
19
#1340000000
0!
0$
0,
01
09
#1345000000
1!
b000 #
1$
b000 &
0'
0(
0*
1,
0.
0/
00
11
03
04
05
06
07
08
19
0;
0<
#1350000000
0!
1"
0$
1%
0,
1-
01
12
09
1:
#1355000000
1!
1$
1,
11
19
#1360000000
0!
0"
0$
0%
0,
0-
01
02
09
0:
#1365000000
1!
b001 #
1$
b001 &
1'
1,
1.
1/
10
11
15
19
#1370000000
0!
0$
0,
01
09
#1375000000
1!
b010 #
1$
b010 &
0'
1(
1,
0.
0/
00
11
13
14
05
16
19
#1380000000
0!
0$
0,
01
09
#1385000000
1!
b011 #
1$
b011 &
1'
1*
1,
1.
1/
10
11
15
17
18
19
#1390000000
0!
0$
0,
01
09
#1395000000
1!
b100 #
1$
b100 &
0'
0(
0*
1,
0.
0/
00
11
03
04
05
06
07
08
19
1;
1<
#1400000000
0!
0$
0,
01
09
#1405000000
1!
b101 #
1$
b101 &
1'
1,
1.
1/
10
11
15
19
#1410000000
0!
0$
0,
01
09
#1415000000
1!
b110 #
1$
b110 &
0'
1(
1,
0.
0/
00
11
13
14
05
16
19
#1420000000
0!
0$
0,
01
09
#1425000000
1!
b111 #
1$
b111 &
1'
1*
1,
1.
1/
10
11
15
17
18
19
#1430000000
0!
0$
0,
01
09
#1435000000
1!
b000 #
1$
b000 &
0'
0(
0*
1,
0.
0/
00
11
03
04
05
06
07
08
19
0;
0<
#1440000000
0!
1"
0$
1%
0,
1-
01
12
09
1:
#1445000000
1!
1$
1,
11
19
#1450000000
0!
0"
0$
0%
0,
0-
01
02
09
0:
#1455000000
1!
b001 #
1$
b001 &
1'
1,
1.
1/
10
11
15
19
#1460000000
0!
0$
0,
01
09
#1465000000
1!
b010 #
1$
b010 &
0'
1(
1,
0.
0/
00
11
13
14
05
16
19
#1470000000
0!
0$
0,
01
09
#1475000000
1!
b011 #
1$
b011 &
1'
1*
1,
1.
1/
10
11
15
17
18
19
#1480000000
0!
0$
0,
01
09
#1485000000
1!
b100 #
1$
b100 &
0'
0(
0*
1,
0.
0/
00
11
03
04
05
06
07
08
19
1;
1<
#1490000000
0!
0$
0,
01
09
#1495000000
1!
b101 #
1$
b101 &
1'
1,
1.
1/
10
11
15
19
#1500000000
0!
0$
0,
01
09
#1505000000
1!
b110 #
1$
b110 &
0'
1(
1,
0.
0/
00
11
13
14
05
16
19
#1510000000
0!
0$
0,
01
09
#1515000000
1!
b111 #
1$
b111 &
1'
1*
1,
1.
1/
10
11
15
17
18
19
#1520000000
0!
0$
0,
01
09
#1525000000
1!
b000 #
1$
b000 &
0'
0(
0*
1,
0.
0/
00
11
03
04
05
06
07
08
19
0;
0<
#1530000000
0!
1"
0$
1%
0,
1-
01
12
09
1:
#1535000000
1!
1$
1,
11
19
#1540000000
0!
0"
0$
0%
0,
0-
01
02
09
0:
#1545000000
1!
b001 #
1$
b001 &
1'
1,
1.
1/
10
11
15
19
#1550000000
0!
0$
0,
01
09
#1555000000
1!
b010 #
1$
b010 &
0'
1(
1,
0.
0/
00
11
13
14
05
16
19
#1560000000
0!
0$
0,
01
09
#1565000000
1!
b011 #
1$
b011 &
1'
1*
1,
1.
1/
10
11
15
17
18
19
#1570000000
0!
0$
0,
01
09
#1575000000
1!
b100 #
1$
b100 &
0'
0(
0*
1,
0.
0/
00
11
03
04
05
06
07
08
19
1;
1<
#1580000000
0!
0$
0,
01
09
#1585000000
1!
b101 #
1$
b101 &
1'
1,
1.
1/
10
11
15
19
#1590000000
0!
0$
0,
01
09
#1595000000
1!
b110 #
1$
b110 &
0'
1(
1,
0.
0/
00
11
13
14
05
16
19
#1600000000
0!
0$
0,
01
09
#1605000000
1!
b111 #
1$
b111 &
1'
1*
1,
1.
1/
10
11
15
17
18
19
#1610000000
0!
0$
0,
01
09
#1615000000
1!
b000 #
1$
b000 &
0'
0(
0*
1,
0.
0/
00
11
03
04
05
06
07
08
19
0;
0<
#1620000000
0!
1"
0$
1%
0,
1-
01
12
09
1:
#1625000000
1!
1$
1,
11
19
#1630000000
0!
0"
0$
0%
0,
0-
01
02
09
0:
#1635000000
1!
b001 #
1$
b001 &
1'
1,
1.
1/
10
11
15
19
#1640000000
0!
0$
0,
01
09
#1645000000
1!
b010 #
1$
b010 &
0'
1(
1,
0.
0/
00
11
13
14
05
16
19
#1650000000
0!
0$
0,
01
09
#1655000000
1!
b011 #
1$
b011 &
1'
1*
1,
1.
1/
10
11
15
17
18
19
#1660000000
0!
0$
0,
01
09
#1665000000
1!
b100 #
1$
b100 &
0'
0(
0*
1,
0.
0/
00
11
03
04
05
06
07
08
19
1;
1<
#1670000000
0!
0$
0,
01
09
#1675000000
1!
b101 #
1$
b101 &
1'
1,
1.
1/
10
11
15
19
#1680000000
0!
0$
0,
01
09
#1685000000
1!
b110 #
1$
b110 &
0'
1(
1,
0.
0/
00
11
13
14
05
16
19
#1690000000
0!
0$
0,
01
09
#1695000000
1!
b111 #
1$
b111 &
1'
1*
1,
1.
1/
10
11
15
17
18
19
#1700000000
0!
0$
0,
01
09
#1705000000
1!
b000 #
1$
b000 &
0'
0(
0*
1,
0.
0/
00
11
03
04
05
06
07
08
19
0;
0<
#1710000000
0!
1"
0$
1%
0,
1-
01
12
09
1:
#1715000000
1!
1$
1,
11
19
#1720000000
0!
0"
0$
0%
0,
0-
01
02
09
0:
#1725000000
1!
b001 #
1$
b001 &
1'
1,
1.
1/
10
11
15
19
#1730000000
0!
0$
0,
01
09
#1735000000
1!
b010 #
1$
b010 &
0'
1(
1,
0.
0/
00
11
13
14
05
16
19
#1740000000
0!
0$
0,
01
09
#1745000000
1!
b011 #
1$
b011 &
1'
1*
1,
1.
1/
10
11
15
17
18
19
#1750000000
0!
0$
0,
01
09
#1755000000
1!
b100 #
1$
b100 &
0'
0(
0*
1,
0.
0/
00
11
03
04
05
06
07
08
19
1;
1<
#1760000000
0!
0$
0,
01
09
#1765000000
1!
b101 #
1$
b101 &
1'
1,
1.
1/
10
11
15
19
#1770000000
0!
0$
0,
01
09
#1775000000
1!
b110 #
1$
b110 &
0'
1(
1,
0.
0/
00
11
13
14
05
16
19
#1780000000
0!
0$
0,
01
09
#1785000000
1!
b111 #
1$
b111 &
1'
1*
1,
1.
1/
10
11
15
17
18
19
#1790000000
0!
0$
0,
01
09
#1795000000
1!
b000 #
1$
b000 &
0'
0(
0*
1,
0.
0/
00
11
03
04
05
06
07
08
19
0;
0<
#1800000000
0!
1"
0$
1%
0,
1-
01
12
09
1:
#1805000000
1!
1$
1,
11
19
#1810000000
0!
0"
0$
0%
0,
0-
01
02
09
0:
#1815000000
1!
b001 #
1$
b001 &
1'
1,
1.
1/
10
11
15
19
#1820000000
0!
0$
0,
01
09
#1825000000
1!
b010 #
1$
b010 &
0'
1(
1,
0.
0/
00
11
13
14
05
16
19
#1830000000
0!
0$
0,
01
09
#1835000000
1!
b011 #
1$
b011 &
1'
1*
1,
1.
1/
10
11
15
17
18
19
#1840000000
0!
0$
0,
01
09
#1845000000
1!
b100 #
1$
b100 &
0'
0(
0*
1,
0.
0/
00
11
03
04
05
06
07
08
19
1;
1<
#1850000000
0!
0$
0,
01
09
#1855000000
1!
b101 #
1$
b101 &
1'
1,
1.
1/
10
11
15
19
#1860000000
0!
0$
0,
01
09
